graphqlapiobject/GraphqlApi/__init__.py
graphqlapiobject/GraphqlApi/gen_params.py
graphqlapiobject/GraphqlApi/graphql_api.py
graphqlapiobject/GraphqlApi/special_graphql_api.py
graphqlapiobject/GraphqlApi/tools.py
graphqlapiobject/User/__init__.py
graphqlapiobject/User/base_user.py
graphqlapiobject/__init__.py
graphqlapiobject/graphql_api_codegen.py
graphqlapiobject-2.0.7.dist-info/WHEEL
graphqlapiobject-2.0.7.dist-info/METADATA
graphqlapiobject-2.0.7.dist-info/RECORD
